easyface/__init__.py
easyface/api.py
easyface/compare.py
easyface/detector.py
easyface/embedder.py
easyface/recognizer.py
easyface/utils.py
easyface_np-0.1.0.dist-info/licenses/LICENSE
easyface_np-0.1.0.dist-info/METADATA
easyface_np-0.1.0.dist-info/WHEEL
easyface_np-0.1.0.dist-info/top_level.txt
easyface_np-0.1.0.dist-info/RECORD
