Metadata-Version: 2.4
Name: easyface-np
Version: 0.1.0
Summary: A lightweight face recognition library without dlib
Author: Nimalpranav
Requires-Python: >=3.10, <3.14
License-File: LICENSE
Requires-Dist: numpy>=1.26
Requires-Dist: opencv-python>=4.8
Requires-Dist: onnxruntime>=1.17
Dynamic: author
Dynamic: license-file
Dynamic: requires-dist
Dynamic: requires-python
Dynamic: summary
